Metadata-Version: 1.1
Name: nashit
Version: 1.0.5
Summary: A Cluster of essential utilities for python
Home-page: https://github.com/nashit93/nashit
Author: Nashit Babber
Author-email: nashit93@gmail.com
License: UNKNOWN
Keywords: pandas numpy download file bulk files
Platform: UNKNOWN
Classifier: Development Status :: 5 - Production/Stable
Classifier: Intended Audience :: Developers
Classifier: Topic :: Software Development :: Build Tools
Classifier: License :: OSI Approved :: MIT License
Classifier: Programming Language :: Python :: 3
Classifier: Programming Language :: Python :: 3.4
Classifier: Programming Language :: Python :: 3.5
Classifier: Programming Language :: Python :: 3.6
